{"id":803,"key":"fc3c71107a1c7c88fc1d3521788b21b3559f23971e1293b976867cd0af12ceda","name":"Rails","threshold":1,"default_language":{"id":64,"locale":"en","english_name":"English","native_name":"English","right_to_left":false,"flag_url":"http://localhost:3000/media_20141208/7/55/1/27/c9262c9538cda82c6.png","status":"published"},"languages":[{"id":64,"locale":"en","english_name":"English","native_name":"English","right_to_left":false,"flag_url":"http://localhost:3000/media_20141208/7/55/1/27/c9262c9538cda82c6.png","status":"published"},{"id":54,"locale":"de","english_name":"German","native_name":"Deutsch","right_to_left":false,"flag_url":"http://localhost:3000/media_20141208/12/42/21/65/7f4dfb2526908b57b.png","status":"published"},{"id":141,"locale":"it","english_name":"Italian","native_name":"Italiano","right_to_left":false,"flag_url":"http://localhost:3000/media_20141208/84/80/50/27/a29c6392ea676b40a.png","status":"published"},{"id":159,"locale":"ko","english_name":"Korean","native_name":"한국어","right_to_left":false,"flag_url":"http://localhost:3000/media_20141208/77/23/21/20/9f91cef570da293ff.png","status":"published"},{"id":101,"locale":"fa","english_name":"Persian","native_name":"فارسی","right_to_left":true,"flag_url":"http://localhost:3000/media_20141208/10/61/38/26/98347096bb7e1214b.png","status":"published"},{"id":233,"locale":"ru","english_name":"Russian","native_name":"Русский","right_to_left":false,"flag_url":"http://localhost:3000/media_20141208/91/67/34/74/6d14cff5e2826c668.png","status":"published"}],"type":"base","created_at":"2015-06-09 00:12:02","updated_at":"2015-06-09 00:12:02","default_locale":"en","features":{"inline_translations":true,"machine_translations":false,"translation_suggestions":true,"decorations":true,"shortcuts":true,"context_rules":true,"language_cases":true,"javascript_sdk":false,"glossary":true,"forum":true,"awards":true,"admin_translations":true,"private_project":true,"language_flags":true},"tokens":{},"css":".tml_not_translated { border-bottom: 1px dotted red; } .tml_translated { border-bottom: 1px dotted green; } .tml_fallback { border-bottom: 1px dotted #e90; } .tml_pending { border-bottom: 1px dotted #e90; } .tml_locked { border-bottom: 1px dotted blue; } .tml_language_case { padding:3px; border: 1px dotted blue; }","shortcuts":{"Ctrl+Shift+S":"Tml.Utils.openShortcuts();","Ctrl+Shift+G":"Tml.Utils.login();","Ctrl+Shift+I":"Tml.Utils.toggleInlineTranslations();","Ctrl+Shift+L":"Tml.UI.LanguageSelector.show(true);","Ctrl+Shift+R":"Tml.Utils.reloadSettings();","Ctrl+Shift+O":"Tml.Utils.logout();"},"tools":{"postoffice":"http://localhost:3003","host":"http://localhost:3002","assets":"http://localhost:3002/assets","javascript":"http://localhost:3002/assets/tools.js","stylesheet":"http://localhost:3002/assets/tools.css"}}